<?xml version="1.0" encoding="utf-8"?>
<TextureAtlas imagePath="Untitled-7.png">
	<!-- Created with Adobe Animate version 20.0.0.17400 -->
	<!-- http://www.adobe.com/products/animate.html -->
	<SubTexture name="DOWN0000" x="0" y="0" width="1166" height="1255"/>
	<SubTexture name="DOWN0001" x="1166" y="0" width="1115" height="1203" frameX="-25" frameY="-25" frameWidth="1166" frameHeight="1255"/>
	<SubTexture name="DOWN0002" x="2281" y="0" width="1062" height="1151" frameX="-51" frameY="-50" frameWidth="1166" frameHeight="1255"/>
	<SubTexture name="DOWN0003" x="3343" y="0" width="1011" height="1096" frameX="-78" frameY="-76" frameWidth="1166" frameHeight="1255"/>
	<SubTexture name="DOWN0004" x="4354" y="0" width="981" height="1041" frameX="-105" frameY="-103" frameWidth="1166" frameHeight="1255"/>
	<SubTexture name="DOWN0005" x="4354" y="0" width="981" height="1041" frameX="-105" frameY="-103" frameWidth="1166" frameHeight="1255"/>
	<SubTexture name="DOWN0006" x="4354" y="0" width="981" height="1041" frameX="-105" frameY="-103" frameWidth="1166" frameHeight="1255"/>
	<SubTexture name="DOWN0007" x="4354" y="0" width="981" height="1041" frameX="-105" frameY="-103" frameWidth="1166" frameHeight="1255"/>
	<SubTexture name="DOWN0008" x="4354" y="0" width="981" height="1041" frameX="-105" frameY="-103" frameWidth="1166" frameHeight="1255"/>
	<SubTexture name="DOWN0009" x="4354" y="0" width="981" height="1041" frameX="-105" frameY="-103" frameWidth="1166" frameHeight="1255"/>
	<SubTexture name="DOWN0010" x="4354" y="0" width="981" height="1041" frameX="-105" frameY="-103" frameWidth="1166" frameHeight="1255"/>
	<SubTexture name="DOWN0011" x="4354" y="0" width="981" height="1041" frameX="-105" frameY="-103" frameWidth="1166" frameHeight="1255"/>
	<SubTexture name="DOWN0012" x="4354" y="0" width="981" height="1041" frameX="-105" frameY="-103" frameWidth="1166" frameHeight="1255"/>
	<SubTexture name="DOWN0013" x="4354" y="0" width="981" height="1041" frameX="-105" frameY="-103" frameWidth="1166" frameHeight="1255"/>
	<SubTexture name="DOWN0014" x="4354" y="0" width="981" height="1041" frameX="-105" frameY="-103" frameWidth="1166" frameHeight="1255"/>
	<SubTexture name="DOWN0015" x="4354" y="0" width="981" height="1041" frameX="-105" frameY="-103" frameWidth="1166" frameHeight="1255"/>
	<SubTexture name="DOWN0016" x="4354" y="0" width="981" height="1041" frameX="-105" frameY="-103" frameWidth="1166" frameHeight="1255"/>
	<SubTexture name="DOWN0017" x="4354" y="0" width="981" height="1041" frameX="-105" frameY="-103" frameWidth="1166" frameHeight="1255"/>
	<SubTexture name="DOWN0018" x="4354" y="0" width="981" height="1041" frameX="-105" frameY="-103" frameWidth="1166" frameHeight="1255"/>
	<SubTexture name="DOWN0019" x="4354" y="0" width="981" height="1041" frameX="-105" frameY="-103" frameWidth="1166" frameHeight="1255"/>
	<SubTexture name="DOWN0020" x="4354" y="0" width="981" height="1041" frameX="-105" frameY="-103" frameWidth="1166" frameHeight="1255"/>
	<SubTexture name="DOWN0021" x="4354" y="0" width="981" height="1041" frameX="-105" frameY="-103" frameWidth="1166" frameHeight="1255"/>
	<SubTexture name="DOWN0022" x="4354" y="0" width="981" height="1041" frameX="-105" frameY="-103" frameWidth="1166" frameHeight="1255"/>
	<SubTexture name="DOWN0023" x="4354" y="0" width="981" height="1041" frameX="-105" frameY="-103" frameWidth="1166" frameHeight="1255"/>
	<SubTexture name="idle0000" x="5335" y="0" width="958" height="997" frameX="-3" frameY="-3" frameWidth="961" frameHeight="1000"/>
	<SubTexture name="idle0001" x="6293" y="0" width="956" height="991" frameX="-2" frameY="-2" frameWidth="961" frameHeight="1000"/>
	<SubTexture name="idle0002" x="0" y="1255" width="954" height="984" frameX="-2" frameY="-2" frameWidth="961" frameHeight="1000"/>
	<SubTexture name="idle0003" x="954" y="1255" width="955" height="978" frameX="-1" frameY="-1" frameWidth="961" frameHeight="1000"/>
	<SubTexture name="idle0004" x="1909" y="1255" width="957" height="971" frameX="0" frameY="0" frameWidth="961" frameHeight="1000"/>
	<SubTexture name="idle0005" x="1909" y="1255" width="957" height="971" frameX="0" frameY="0" frameWidth="961" frameHeight="1000"/>
	<SubTexture name="idle0006" x="1909" y="1255" width="957" height="971" frameX="0" frameY="0" frameWidth="961" frameHeight="1000"/>
	<SubTexture name="idle0007" x="1909" y="1255" width="957" height="971" frameX="0" frameY="0" frameWidth="961" frameHeight="1000"/>
	<SubTexture name="idle0008" x="1909" y="1255" width="957" height="971" frameX="0" frameY="0" frameWidth="961" frameHeight="1000"/>
	<SubTexture name="idle0009" x="1909" y="1255" width="957" height="971" frameX="0" frameY="0" frameWidth="961" frameHeight="1000"/>
	<SubTexture name="idle0010" x="1909" y="1255" width="957" height="971" frameX="0" frameY="0" frameWidth="961" frameHeight="1000"/>
	<SubTexture name="idle0011" x="1909" y="1255" width="957" height="971" frameX="0" frameY="0" frameWidth="961" frameHeight="1000"/>
	<SubTexture name="idle0012" x="1909" y="1255" width="957" height="971" frameX="0" frameY="0" frameWidth="961" frameHeight="1000"/>
	<SubTexture name="idle0013" x="1909" y="1255" width="957" height="971" frameX="0" frameY="0" frameWidth="961" frameHeight="1000"/>
	<SubTexture name="idle0014" x="1909" y="1255" width="957" height="971" frameX="0" frameY="0" frameWidth="961" frameHeight="1000"/>
	<SubTexture name="idle0015" x="1909" y="1255" width="957" height="971" frameX="0" frameY="0" frameWidth="961" frameHeight="1000"/>
	<SubTexture name="idle0016" x="1909" y="1255" width="957" height="971" frameX="0" frameY="0" frameWidth="961" frameHeight="1000"/>
	<SubTexture name="idle0017" x="1909" y="1255" width="957" height="971" frameX="0" frameY="0" frameWidth="961" frameHeight="1000"/>
	<SubTexture name="idle0018" x="1909" y="1255" width="957" height="971" frameX="0" frameY="0" frameWidth="961" frameHeight="1000"/>
	<SubTexture name="idle0019" x="1909" y="1255" width="957" height="971" frameX="0" frameY="0" frameWidth="961" frameHeight="1000"/>
	<SubTexture name="idle0020" x="1909" y="1255" width="957" height="971" frameX="0" frameY="0" frameWidth="961" frameHeight="1000"/>
	<SubTexture name="idle0021" x="1909" y="1255" width="957" height="971" frameX="0" frameY="0" frameWidth="961" frameHeight="1000"/>
	<SubTexture name="idle0022" x="1909" y="1255" width="957" height="971" frameX="0" frameY="0" frameWidth="961" frameHeight="1000"/>
	<SubTexture name="idle0023" x="1909" y="1255" width="957" height="971" frameX="0" frameY="0" frameWidth="961" frameHeight="1000"/>
	<SubTexture name="left0000" x="2866" y="1255" width="1203" height="1197"/>
	<SubTexture name="left0001" x="4069" y="1255" width="1152" height="1145" frameX="-32" frameY="-27" frameWidth="1203" frameHeight="1197"/>
	<SubTexture name="left0002" x="5221" y="1255" width="1092" height="1084" frameX="-68" frameY="-58" frameWidth="1203" frameHeight="1197"/>
	<SubTexture name="left0003" x="6313" y="1255" width="1025" height="1016" frameX="-108" frameY="-93" frameWidth="1203" frameHeight="1197"/>
	<SubTexture name="left0004" x="0" y="2452" width="952" height="947" frameX="-150" frameY="-131" frameWidth="1203" frameHeight="1197"/>
	<SubTexture name="left0005" x="0" y="2452" width="952" height="947" frameX="-150" frameY="-131" frameWidth="1203" frameHeight="1197"/>
	<SubTexture name="left0006" x="0" y="2452" width="952" height="947" frameX="-150" frameY="-131" frameWidth="1203" frameHeight="1197"/>
	<SubTexture name="left0007" x="0" y="2452" width="952" height="947" frameX="-150" frameY="-131" frameWidth="1203" frameHeight="1197"/>
	<SubTexture name="left0008" x="0" y="2452" width="952" height="947" frameX="-150" frameY="-131" frameWidth="1203" frameHeight="1197"/>
	<SubTexture name="left0009" x="0" y="2452" width="952" height="947" frameX="-150" frameY="-131" frameWidth="1203" frameHeight="1197"/>
	<SubTexture name="left0010" x="0" y="2452" width="952" height="947" frameX="-150" frameY="-131" frameWidth="1203" frameHeight="1197"/>
	<SubTexture name="left0011" x="0" y="2452" width="952" height="947" frameX="-150" frameY="-131" frameWidth="1203" frameHeight="1197"/>
	<SubTexture name="left0012" x="0" y="2452" width="952" height="947" frameX="-150" frameY="-131" frameWidth="1203" frameHeight="1197"/>
	<SubTexture name="left0013" x="0" y="2452" width="952" height="947" frameX="-150" frameY="-131" frameWidth="1203" frameHeight="1197"/>
	<SubTexture name="left0014" x="0" y="2452" width="952" height="947" frameX="-150" frameY="-131" frameWidth="1203" frameHeight="1197"/>
	<SubTexture name="left0015" x="0" y="2452" width="952" height="947" frameX="-150" frameY="-131" frameWidth="1203" frameHeight="1197"/>
	<SubTexture name="left0016" x="0" y="2452" width="952" height="947" frameX="-150" frameY="-131" frameWidth="1203" frameHeight="1197"/>
	<SubTexture name="left0017" x="0" y="2452" width="952" height="947" frameX="-150" frameY="-131" frameWidth="1203" frameHeight="1197"/>
	<SubTexture name="left0018" x="0" y="2452" width="952" height="947" frameX="-150" frameY="-131" frameWidth="1203" frameHeight="1197"/>
	<SubTexture name="left0019" x="0" y="2452" width="952" height="947" frameX="-150" frameY="-131" frameWidth="1203" frameHeight="1197"/>
	<SubTexture name="left0020" x="0" y="2452" width="952" height="947" frameX="-150" frameY="-131" frameWidth="1203" frameHeight="1197"/>
	<SubTexture name="left0021" x="0" y="2452" width="952" height="947" frameX="-150" frameY="-131" frameWidth="1203" frameHeight="1197"/>
	<SubTexture name="left0022" x="0" y="2452" width="952" height="947" frameX="-150" frameY="-131" frameWidth="1203" frameHeight="1197"/>
	<SubTexture name="left0023" x="0" y="2452" width="952" height="947" frameX="-150" frameY="-131" frameWidth="1203" frameHeight="1197"/>
	<SubTexture name="right0000" x="952" y="2452" width="1093" height="1095"/>
	<SubTexture name="right0001" x="2045" y="2452" width="1060" height="1060" frameX="-2" frameY="-21" frameWidth="1093" frameHeight="1095"/>
	<SubTexture name="right0002" x="3105" y="2452" width="1026" height="1023" frameX="-4" frameY="-44" frameWidth="1093" frameHeight="1095"/>
	<SubTexture name="right0003" x="4131" y="2452" width="989" height="985" frameX="-8" frameY="-67" frameWidth="1093" frameHeight="1095"/>
	<SubTexture name="right0004" x="5120" y="2452" width="967" height="952" frameX="-11" frameY="-91" frameWidth="1093" frameHeight="1095"/>
	<SubTexture name="right0005" x="5120" y="2452" width="967" height="952" frameX="-11" frameY="-91" frameWidth="1093" frameHeight="1095"/>
	<SubTexture name="right0006" x="5120" y="2452" width="967" height="952" frameX="-11" frameY="-91" frameWidth="1093" frameHeight="1095"/>
	<SubTexture name="right0007" x="5120" y="2452" width="967" height="952" frameX="-11" frameY="-91" frameWidth="1093" frameHeight="1095"/>
	<SubTexture name="right0008" x="5120" y="2452" width="967" height="952" frameX="-11" frameY="-91" frameWidth="1093" frameHeight="1095"/>
	<SubTexture name="right0009" x="5120" y="2452" width="967" height="952" frameX="-11" frameY="-91" frameWidth="1093" frameHeight="1095"/>
	<SubTexture name="right0010" x="5120" y="2452" width="967" height="952" frameX="-11" frameY="-91" frameWidth="1093" frameHeight="1095"/>
	<SubTexture name="right0011" x="5120" y="2452" width="967" height="952" frameX="-11" frameY="-91" frameWidth="1093" frameHeight="1095"/>
	<SubTexture name="right0012" x="5120" y="2452" width="967" height="952" frameX="-11" frameY="-91" frameWidth="1093" frameHeight="1095"/>
	<SubTexture name="right0013" x="5120" y="2452" width="967" height="952" frameX="-11" frameY="-91" frameWidth="1093" frameHeight="1095"/>
	<SubTexture name="right0014" x="5120" y="2452" width="967" height="952" frameX="-11" frameY="-91" frameWidth="1093" frameHeight="1095"/>
	<SubTexture name="right0015" x="5120" y="2452" width="967" height="952" frameX="-11" frameY="-91" frameWidth="1093" frameHeight="1095"/>
	<SubTexture name="right0016" x="5120" y="2452" width="967" height="952" frameX="-11" frameY="-91" frameWidth="1093" frameHeight="1095"/>
	<SubTexture name="right0017" x="5120" y="2452" width="967" height="952" frameX="-11" frameY="-91" frameWidth="1093" frameHeight="1095"/>
	<SubTexture name="right0018" x="5120" y="2452" width="967" height="952" frameX="-11" frameY="-91" frameWidth="1093" frameHeight="1095"/>
	<SubTexture name="right0019" x="5120" y="2452" width="967" height="952" frameX="-11" frameY="-91" frameWidth="1093" frameHeight="1095"/>
	<SubTexture name="right0020" x="5120" y="2452" width="967" height="952" frameX="-11" frameY="-91" frameWidth="1093" frameHeight="1095"/>
	<SubTexture name="right0021" x="5120" y="2452" width="967" height="952" frameX="-11" frameY="-91" frameWidth="1093" frameHeight="1095"/>
	<SubTexture name="right0022" x="5120" y="2452" width="967" height="952" frameX="-11" frameY="-91" frameWidth="1093" frameHeight="1095"/>
	<SubTexture name="right0023" x="5120" y="2452" width="967" height="952" frameX="-11" frameY="-91" frameWidth="1093" frameHeight="1095"/>
	<SubTexture name="up0000" x="6087" y="2452" width="1148" height="1167"/>
	<SubTexture name="up0001" x="0" y="3619" width="1128" height="1148" frameX="-13" frameY="-19" frameWidth="1148" frameHeight="1167"/>
	<SubTexture name="up0002" x="1128" y="3619" width="1107" height="1127" frameX="-27" frameY="-40" frameWidth="1148" frameHeight="1167"/>
	<SubTexture name="up0003" x="2235" y="3619" width="1085" height="1106" frameX="-41" frameY="-61" frameWidth="1148" frameHeight="1167"/>
	<SubTexture name="up0004" x="3320" y="3619" width="1063" height="1085" frameX="-55" frameY="-82" frameWidth="1148" frameHeight="1167"/>
	<SubTexture name="up0005" x="3320" y="3619" width="1063" height="1085" frameX="-55" frameY="-82" frameWidth="1148" frameHeight="1167"/>
	<SubTexture name="up0006" x="3320" y="3619" width="1063" height="1085" frameX="-55" frameY="-82" frameWidth="1148" frameHeight="1167"/>
	<SubTexture name="up0007" x="3320" y="3619" width="1063" height="1085" frameX="-55" frameY="-82" frameWidth="1148" frameHeight="1167"/>
	<SubTexture name="up0008" x="3320" y="3619" width="1063" height="1085" frameX="-55" frameY="-82" frameWidth="1148" frameHeight="1167"/>
	<SubTexture name="up0009" x="3320" y="3619" width="1063" height="1085" frameX="-55" frameY="-82" frameWidth="1148" frameHeight="1167"/>
	<SubTexture name="up0010" x="3320" y="3619" width="1063" height="1085" frameX="-55" frameY="-82" frameWidth="1148" frameHeight="1167"/>
	<SubTexture name="up0011" x="3320" y="3619" width="1063" height="1085" frameX="-55" frameY="-82" frameWidth="1148" frameHeight="1167"/>
	<SubTexture name="up0012" x="3320" y="3619" width="1063" height="1085" frameX="-55" frameY="-82" frameWidth="1148" frameHeight="1167"/>
	<SubTexture name="up0013" x="3320" y="3619" width="1063" height="1085" frameX="-55" frameY="-82" frameWidth="1148" frameHeight="1167"/>
	<SubTexture name="up0014" x="3320" y="3619" width="1063" height="1085" frameX="-55" frameY="-82" frameWidth="1148" frameHeight="1167"/>
	<SubTexture name="up0015" x="3320" y="3619" width="1063" height="1085" frameX="-55" frameY="-82" frameWidth="1148" frameHeight="1167"/>
	<SubTexture name="up0016" x="3320" y="3619" width="1063" height="1085" frameX="-55" frameY="-82" frameWidth="1148" frameHeight="1167"/>
	<SubTexture name="up0017" x="3320" y="3619" width="1063" height="1085" frameX="-55" frameY="-82" frameWidth="1148" frameHeight="1167"/>
	<SubTexture name="up0018" x="3320" y="3619" width="1063" height="1085" frameX="-55" frameY="-82" frameWidth="1148" frameHeight="1167"/>
	<SubTexture name="up0019" x="3320" y="3619" width="1063" height="1085" frameX="-55" frameY="-82" frameWidth="1148" frameHeight="1167"/>
	<SubTexture name="up0020" x="3320" y="3619" width="1063" height="1085" frameX="-55" frameY="-82" frameWidth="1148" frameHeight="1167"/>
	<SubTexture name="up0021" x="3320" y="3619" width="1063" height="1085" frameX="-55" frameY="-82" frameWidth="1148" frameHeight="1167"/>
	<SubTexture name="up0022" x="3320" y="3619" width="1063" height="1085" frameX="-55" frameY="-82" frameWidth="1148" frameHeight="1167"/>
	<SubTexture name="up0023" x="3320" y="3619" width="1063" height="1085" frameX="-55" frameY="-82" frameWidth="1148" frameHeight="1167"/>
</TextureAtlas>
